{
 "nodes": [
  {
   "id": "SELF",
   "label": "M. Asif Khan",
   "self": true,
   "val": 24
  },
  {
   "id": "Tan TW",
   "label": "Tin Wee Tan",
   "val": 22,
   "papers": 22,
   "linktype": "Scholar",
   "url": "https://scholar.google.com/citations?user=S-2B094AAAAJ"
  },
  {
   "id": "Brusic V",
   "label": "Vladimir Brusic",
   "val": 17,
   "papers": 17,
   "linktype": "ORCID",
   "url": "https://orcid.org/0000-0003-0523-5266"
  },
  {
   "id": "August JT",
   "label": "J. Thomas August",
   "val": 17,
   "papers": 17,
   "linktype": "None"
  },
  {
   "id": "Chong LC",
   "label": "Li Chuin Chong",
   "val": 9,
   "papers": 9,
   "linktype": "ORCID",
   "url": "https://orcid.org/0000-0002-3574-1365"
  },
  {
   "id": "Srinivasan KN",
   "label": "K. N. Srinivasan",
   "val": 8,
   "papers": 8,
   "linktype": "None"
  },
  {
   "id": "Hu Y",
   "label": "Yongli Hu",
   "val": 7,
   "papers": 7,
   "linktype": "ORCID",
   "url": "https://orcid.org/0000-0002-5205-4911"
  },
  {
   "id": "Miotto O",
   "label": "Olivo Miotto",
   "val": 7,
   "papers": 7,
   "linktype": "ORCID",
   "url": "https://orcid.org/0000-0001-8060-6771"
  },
  {
   "id": "Tan PT",
   "label": "Paul T. J. Tan",
   "val": 7,
   "papers": 7,
   "linktype": "None"
  },
  {
   "id": "Marques ET",
   "label": "Ernesto T. A. Marques",
   "val": 6,
   "papers": 6,
   "linktype": "ORCID",
   "url": "https://orcid.org/0000-0003-3826-9358"
  },
  {
   "id": "Salmon J",
   "label": "Jerome Salmon",
   "val": 6,
   "papers": 6,
   "linktype": "None"
  },
  {
   "id": "Zhang GL",
   "label": "Guang Lan Zhang",
   "val": 5,
   "papers": 5,
   "linktype": "Scholar",
   "url": "https://scholar.google.com/citations?user=iLRPgD4AAAAJ"
  },
  {
   "id": "Ranganathan S",
   "label": "Shoba Ranganathan",
   "val": 5,
   "papers": 5,
   "linktype": "ORCID",
   "url": "https://orcid.org/0000-0002-8290-813X"
  },
  {
   "id": "Sekaran SD",
   "label": "Shamala Devi Sekaran",
   "val": 5,
   "papers": 5,
   "linktype": "ORCID",
   "url": "https://orcid.org/0000-0002-0478-0425"
  },
  {
   "id": "Koh JL",
   "label": "Judice L.Y. Koh",
   "val": 5,
   "papers": 5,
   "linktype": "ORCID",
   "url": "https://orcid.org/0000-0002-8454-7040"
  },
  {
   "id": "Heiny AT",
   "label": "A. T. Heiny",
   "val": 5,
   "papers": 5,
   "linktype": "Scholar",
   "url": "https://scholar.google.com/citations?user=-BNUl18AAAAJ&hl=en"
  },
  {
   "id": "Seah SH",
   "label": "S. H. Seah",
   "val": 4,
   "papers": 4,
   "linktype": "None"
  },
  {
   "id": "Lim SJ",
   "label": "Shen Jean Lim",
   "val": 4,
   "papers": 4,
   "linktype": "ORCID",
   "url": "https://orcid.org/0000-0003-4578-5318"
  },
  {
   "id": "Silva M",
   "label": "Mark De Silva",
   "val": 4,
   "papers": 4,
   "linktype": "None"
  },
  {
   "id": "Lim KS",
   "label": "K. S. Lim",
   "val": 4,
   "papers": 4,
   "linktype": "None"
  },
  {
   "id": "Nascimento EJ",
   "label": "Eduardo J. M. Nascimento",
   "val": 4,
   "papers": 4,
   "linktype": "Scholar",
   "url": "https://scholar.google.com/citations?user=qQ4mxH4AAAAJ"
  }
 ],
 "links": [
  {
   "s": "SELF",
   "t": "Tan TW",
   "w": 22
  },
  {
   "s": "SELF",
   "t": "Brusic V",
   "w": 17
  },
  {
   "s": "SELF",
   "t": "August JT",
   "w": 17
  },
  {
   "s": "SELF",
   "t": "Chong LC",
   "w": 9
  },
  {
   "s": "SELF",
   "t": "Srinivasan KN",
   "w": 8
  },
  {
   "s": "SELF",
   "t": "Hu Y",
   "w": 7
  },
  {
   "s": "SELF",
   "t": "Miotto O",
   "w": 7
  },
  {
   "s": "SELF",
   "t": "Tan PT",
   "w": 7
  },
  {
   "s": "SELF",
   "t": "Marques ET",
   "w": 6
  },
  {
   "s": "SELF",
   "t": "Salmon J",
   "w": 6
  },
  {
   "s": "SELF",
   "t": "Zhang GL",
   "w": 5
  },
  {
   "s": "SELF",
   "t": "Ranganathan S",
   "w": 5
  },
  {
   "s": "SELF",
   "t": "Sekaran SD",
   "w": 5
  },
  {
   "s": "SELF",
   "t": "Koh JL",
   "w": 5
  },
  {
   "s": "SELF",
   "t": "Heiny AT",
   "w": 5
  },
  {
   "s": "SELF",
   "t": "Seah SH",
   "w": 4
  },
  {
   "s": "SELF",
   "t": "Lim SJ",
   "w": 4
  },
  {
   "s": "SELF",
   "t": "Silva M",
   "w": 4
  },
  {
   "s": "SELF",
   "t": "Lim KS",
   "w": 4
  },
  {
   "s": "SELF",
   "t": "Nascimento EJ",
   "w": 4
  },
  {
   "s": "August JT",
   "t": "Brusic V",
   "w": 10
  },
  {
   "s": "August JT",
   "t": "Srinivasan KN",
   "w": 8
  },
  {
   "s": "Brusic V",
   "t": "Srinivasan KN",
   "w": 8
  },
  {
   "s": "Brusic V",
   "t": "Tan TW",
   "w": 7
  },
  {
   "s": "August JT",
   "t": "Tan TW",
   "w": 7
  },
  {
   "s": "Miotto O",
   "t": "Tan TW",
   "w": 6
  },
  {
   "s": "Brusic V",
   "t": "Koh JL",
   "w": 5
  },
  {
   "s": "August JT",
   "t": "Heiny AT",
   "w": 5
  },
  {
   "s": "Brusic V",
   "t": "Heiny AT",
   "w": 5
  },
  {
   "s": "Heiny AT",
   "t": "Srinivasan KN",
   "w": 5
  },
  {
   "s": "August JT",
   "t": "Marques ET",
   "w": 5
  },
  {
   "s": "August JT",
   "t": "Miotto O",
   "w": 5
  },
  {
   "s": "Brusic V",
   "t": "Miotto O",
   "w": 5
  },
  {
   "s": "August JT",
   "t": "Zhang GL",
   "w": 5
  },
  {
   "s": "Brusic V",
   "t": "Zhang GL",
   "w": 5
  },
  {
   "s": "Srinivasan KN",
   "t": "Zhang GL",
   "w": 5
  },
  {
   "s": "Ranganathan S",
   "t": "Tan TW",
   "w": 5
  },
  {
   "s": "Brusic V",
   "t": "Tan PT",
   "w": 5
  },
  {
   "s": "Brusic V",
   "t": "Seah SH",
   "w": 4
  },
  {
   "s": "Koh JL",
   "t": "Seah SH",
   "w": 4
  },
  {
   "s": "Heiny AT",
   "t": "Tan TW",
   "w": 4
  },
  {
   "s": "Srinivasan KN",
   "t": "Tan TW",
   "w": 4
  },
  {
   "s": "August JT",
   "t": "Nascimento EJ",
   "w": 4
  },
  {
   "s": "August JT",
   "t": "Salmon J",
   "w": 4
  },
  {
   "s": "Marques ET",
   "t": "Nascimento EJ",
   "w": 4
  },
  {
   "s": "Marques ET",
   "t": "Salmon J",
   "w": 4
  },
  {
   "s": "Marques ET",
   "t": "Tan TW",
   "w": 4
  },
  {
   "s": "Miotto O",
   "t": "Salmon J",
   "w": 4
  },
  {
   "s": "Salmon J",
   "t": "Tan TW",
   "w": 4
  },
  {
   "s": "Hu Y",
   "t": "Tan TW",
   "w": 4
  },
  {
   "s": "Lim KS",
   "t": "Silva M",
   "w": 4
  },
  {
   "s": "Lim KS",
   "t": "Tan TW",
   "w": 4
  },
  {
   "s": "Lim SJ",
   "t": "Tan TW",
   "w": 4
  },
  {
   "s": "Silva M",
   "t": "Tan TW",
   "w": 4
  },
  {
   "s": "Koh JL",
   "t": "Tan PT",
   "w": 4
  },
  {
   "s": "Brusic V",
   "t": "Marques ET",
   "w": 3
  },
  {
   "s": "Brusic V",
   "t": "Nascimento EJ",
   "w": 3
  },
  {
   "s": "Brusic V",
   "t": "Salmon J",
   "w": 3
  },
  {
   "s": "Heiny AT",
   "t": "Miotto O",
   "w": 3
  },
  {
   "s": "Marques ET",
   "t": "Miotto O",
   "w": 3
  },
  {
   "s": "Miotto O",
   "t": "Nascimento EJ",
   "w": 3
  },
  {
   "s": "Miotto O",
   "t": "Srinivasan KN",
   "w": 3
  },
  {
   "s": "Nascimento EJ",
   "t": "Salmon J",
   "w": 3
  },
  {
   "s": "Nascimento EJ",
   "t": "Tan TW",
   "w": 3
  },
  {
   "s": "Heiny AT",
   "t": "Zhang GL",
   "w": 3
  },
  {
   "s": "Lim KS",
   "t": "Lim SJ",
   "w": 3
  },
  {
   "s": "Lim SJ",
   "t": "Silva M",
   "w": 3
  },
  {
   "s": "August JT",
   "t": "Hu Y",
   "w": 3
  },
  {
   "s": "Seah SH",
   "t": "Tan PT",
   "w": 3
  },
  {
   "s": "Heiny AT",
   "t": "Marques ET",
   "w": 2
  },
  {
   "s": "Heiny AT",
   "t": "Nascimento EJ",
   "w": 2
  },
  {
   "s": "Heiny AT",
   "t": "Salmon J",
   "w": 2
  },
  {
   "s": "Marques ET",
   "t": "Srinivasan KN",
   "w": 2
  },
  {
   "s": "Nascimento EJ",
   "t": "Srinivasan KN",
   "w": 2
  },
  {
   "s": "Salmon J",
   "t": "Srinivasan KN",
   "w": 2
  },
  {
   "s": "Miotto O",
   "t": "Zhang GL",
   "w": 2
  },
  {
   "s": "Tan TW",
   "t": "Zhang GL",
   "w": 2
  },
  {
   "s": "Hu Y",
   "t": "Lim KS",
   "w": 2
  },
  {
   "s": "Hu Y",
   "t": "Lim SJ",
   "w": 2
  },
  {
   "s": "Hu Y",
   "t": "Silva M",
   "w": 2
  },
  {
   "s": "Lim SJ",
   "t": "Ranganathan S",
   "w": 2
  },
  {
   "s": "Lim KS",
   "t": "Ranganathan S",
   "w": 2
  },
  {
   "s": "Ranganathan S",
   "t": "Silva M",
   "w": 2
  },
  {
   "s": "August JT",
   "t": "Tan PT",
   "w": 2
  },
  {
   "s": "Hu Y",
   "t": "Miotto O",
   "w": 2
  },
  {
   "s": "Koh JL",
   "t": "Tan TW",
   "w": 1
  },
  {
   "s": "Seah SH",
   "t": "Tan TW",
   "w": 1
  },
  {
   "s": "Marques ET",
   "t": "Zhang GL",
   "w": 1
  },
  {
   "s": "Nascimento EJ",
   "t": "Zhang GL",
   "w": 1
  },
  {
   "s": "Salmon J",
   "t": "Zhang GL",
   "w": 1
  },
  {
   "s": "Hu Y",
   "t": "Tan PT",
   "w": 1
  },
  {
   "s": "Tan PT",
   "t": "Tan TW",
   "w": 1
  },
  {
   "s": "Brusic V",
   "t": "Hu Y",
   "w": 1
  },
  {
   "s": "Hu Y",
   "t": "Marques ET",
   "w": 1
  },
  {
   "s": "Hu Y",
   "t": "Salmon J",
   "w": 1
  },
  {
   "s": "August JT",
   "t": "Chong LC",
   "w": 1
  },
  {
   "s": "Hu Y",
   "t": "Sekaran SD",
   "w": 1
  }
 ],
 "total_unique": 53,
 "source": "CV master publication list (peer-reviewed only), audited"
}